anki_ocr_gui/__init__.py
anki_ocr_gui/anki_ocr_gui.py
anki_ocr_gui/cli_entry.py
anki_ocr_gui-0.1.dist-info/LICENSE.md
anki_ocr_gui-0.1.dist-info/METADATA
anki_ocr_gui-0.1.dist-info/WHEEL
anki_ocr_gui-0.1.dist-info/entry_points.txt
anki_ocr_gui-0.1.dist-info/top_level.txt
anki_ocr_gui-0.1.dist-info/RECORD
